phonexia_grapheme_to_phoneme_conversion_client.py
phonexia_grapheme_to_phoneme_conversion_client-1.0.0.dist-info/METADATA
phonexia_grapheme_to_phoneme_conversion_client-1.0.0.dist-info/WHEEL
phonexia_grapheme_to_phoneme_conversion_client-1.0.0.dist-info/entry_points.txt
phonexia_grapheme_to_phoneme_conversion_client-1.0.0.dist-info/top_level.txt
phonexia_grapheme_to_phoneme_conversion_client-1.0.0.dist-info/RECORD
