Metadata-Version: 2.4
Name: phonexia-grapheme-to-phoneme-conversion-client
Version: 1.0.0
Summary: Grapheme to Phoneme Conversion Client
Author-email: Phonexia <info@phonexia.com>
Keywords: grpc,grapheme,phoneme,g2p,conversion,pronunciation
Requires-Python: >=3.9
Requires-Dist: phonexia-grpc>=2.28.0
Requires-Dist: typer>=0.16.0
